{"changelog.md":"3dd1a843","extra_car-track.md":"2829642b","index.md":"9ac6d6e0","map_control.md":"d2492f75","map_map.md":"878f9fe3","mousetool_mousetool.md":"fcd6d174","overlay_circle.md":"29feb8f5","overlay_cloud-marker-collection.md":"6354ba41","overlay_infowindow.md":"9e432ae5","overlay_label.md":"301306d2","overlay_marker-clusterer.md":"3d8db2d4","overlay_marker.md":"8dfdfe58","overlay_polygon.md":"7c990e57","overlay_polyline.md":"211b3472","overlay_rectangle.md":"3274e819","service_route.md":"9f2091c4","service_search.md":"c4a78127","tilelayer_gridline-layer.md":"98974789","tilelayer_tilelayer-tdt.md":"0848386b","tilelayer_tilelayer-wms.md":"58fa4756","tilelayer_tilelayer.md":"e264ae1e"}
